pybars/__init__.py
pybars/_compiler.py
pybars/_templates/__init__.py
pybars3_wheel-0.9.7.post20241027.dist-info/LICENSE
pybars3_wheel-0.9.7.post20241027.dist-info/METADATA
pybars3_wheel-0.9.7.post20241027.dist-info/WHEEL
pybars3_wheel-0.9.7.post20241027.dist-info/top_level.txt
pybars3_wheel-0.9.7.post20241027.dist-info/RECORD
