Metadata-Version: 2.1
Name: pybars3-wheel
Version: 0.9.7.post20241027
Summary: Handlebars.js templating for Python 3 and 2
Home-page: https://github.com/wbond/pybars3
Author: wbond, mjumbewu
Author-email: will@wbond.net, mjumbewu@gmail.com
Classifier: Development Status :: 4 - Beta
Classifier: Intended Audience :: Developers
Classifier: License :: OSI Approved :: GNU Library or Lesser General Public License (LGPL)
Classifier: Operating System :: OS Independent
Classifier: Programming Language :: Python :: 2
Classifier: Programming Language :: Python :: 2.7
Classifier: Programming Language :: Python :: 3
Classifier: Programming Language :: Python :: 3.3
Classifier: Programming Language :: Python :: 3.4
License-File: LICENSE
Requires-Dist: PyMeta3-wheel >=0.5.1
